wordfilter/__init__.py
wordfilter/badwords.json
wordfilter/wordfilter.py
wordfilter-0.2.7.dist-info/LICENSE-MIT
wordfilter-0.2.7.dist-info/METADATA
wordfilter-0.2.7.dist-info/WHEEL
wordfilter-0.2.7.dist-info/top_level.txt
wordfilter-0.2.7.dist-info/RECORD
