Metadata-Version: 2.1
Name: wordfilter
Version: 0.2.7
Summary: A small module meant for use in text generators that lets
Home-page: https://github.com/dariusk/wordfilter
Author: Darius Kazemi
License: MIT
Platform: UNKNOWN
Classifier: Programming Language :: Python :: 3
Classifier: Topic :: Communications
Classifier: Topic :: Text Processing :: Linguistic
Classifier: License :: OSI Approved :: MIT License
Classifier: Natural Language :: English
Classifier: Intended Audience :: Developers
Requires-Python: >=3
